{
    "version": "0.4",
    "title": "Block: Intro",
    "type": "section",
    "metadata": {
        "template_type": "section-other",
        "include_in_zip": "1",
        "elementor_pro_required": "1",
        "wp_page_template": "elementor_header_footer"
    },
    "content": [
        {
            "id": "1e261fef",
            "settings": {
                "padding": {
                    "unit": "px",
                    "top": "80",
                    "right": "0",
                    "bottom": "80",
                    "left": "0",
                    "isLinked": false
                },
                "_title": "Intro"
            },
            "elements": [
                {
                    "id": "1286d960",
                    "settings": {
                        "_column_size": 100,
                        "_inline_size": null
                    },
                    "elements": [
                        {
                            "id": "34bd73f",
                            "settings": {
                                "title": "Portfolio",
                                "header_size": "h6",
                                "align": "center",
                                "__globals__": {
                                    "title_color": "globals\/colors?id=c6d5909",
                                    "typography_typography": "globals\/typography?id=2fecf69"
                                }
                            },
                            "elements": [],
                            "isInner": false,
                            "widgetType": "heading",
                            "elType": "widget"
                        },
                        {
                            "id": "1ae14c16",
                            "settings": {
                                "title": " Pellentesque diam <br> volutpat commodo sed",
                                "header_size": "h3",
                                "align": "center",
                                "_margin": {
                                    "unit": "px",
                                    "top": "0",
                                    "right": "0",
                                    "bottom": "30",
                                    "left": "0",
                                    "isLinked": false
                                },
                                "__globals__": {
                                    "title_color": "globals\/colors?id=c6d5909",
                                    "typography_typography": "globals\/typography?id=023ac4e"
                                }
                            },
                            "elements": [],
                            "isInner": false,
                            "widgetType": "heading",
                            "elType": "widget"
                        },
                        {
                            "id": "7116fb3c",
                            "settings": {
                                "width": {
                                    "unit": "px",
                                    "size": 40,
                                    "sizes": []
                                },
                                "text": "Divider",
                                "weight": {
                                    "unit": "px",
                                    "size": 2,
                                    "sizes": []
                                },
                                "gap": {
                                    "unit": "px",
                                    "size": 5,
                                    "sizes": []
                                },
                                "_margin": {
                                    "unit": "px",
                                    "top": "10",
                                    "right": "0",
                                    "bottom": "0",
                                    "left": "0",
                                    "isLinked": false
                                },
                                "align": "center",
                                "__globals__": {
                                    "color": "globals\/colors?id=accent"
                                }
                            },
                            "elements": [],
                            "isInner": false,
                            "widgetType": "divider",
                            "elType": "widget"
                        }
                    ],
                    "isInner": false,
                    "elType": "column"
                }
            ],
            "isInner": false,
            "elType": "section"
        }
    ]
}